<annotation verified="yes">
                                    <folder>Annotation</folder>
                                    <filename>0499</filename>
                                    <path>D:\DataSets\mine\1\mine_output_pascal_voc\JPEGImages\0499.jpg</path>
                                    <source>
                                        <database>Unknown</database>
                                    </source>
                                    <size>
                                        <width>1024</width>
                                        <height>768</height>
                                        <depth>3</depth>
                                    </size>
                                    <segmented>0</segmented>
                                    <object>
                                            <name>truck</name>
                                            <pose>Unspecified</pose>
                                            <bndbox>
                                                <xmin>281</xmin>
                                                <ymin>343</ymin>
                                                <xmax>351</xmax>
                                                <ymax>420</ymax>
                                            </bndbox>
                                    </object>
                                    
                                    <object>
                                            <name>car</name>
                                            <pose>Unspecified</pose>
                                            <bndbox>
                                                <xmin>324</xmin>
                                                <ymin>289</ymin>
                                                <xmax>397</xmax>
                                                <ymax>355</ymax>
                                            </bndbox>
                                    </object>
                                    
                                    <object>
                                            <name>car</name>
                                            <pose>Unspecified</pose>
                                            <bndbox>
                                                <xmin>734</xmin>
                                                <ymin>332</ymin>
                                                <xmax>806</xmax>
                                                <ymax>402</ymax>
                                            </bndbox>
                                    </object>
                                    </annotation>