<annotation verified="yes">
                                    <folder>Annotation</folder>
                                    <filename>0910</filename>
                                    <path>D:\DataSets\mine\2\mine2_output_pascal_voc\JPEGImages\0910.jpg</path>
                                    <source>
                                        <database>Unknown</database>
                                    </source>
                                    <size>
                                        <width>1024</width>
                                        <height>768</height>
                                        <depth>3</depth>
                                    </size>
                                    <segmented>0</segmented>
                                    <object>
                                            <name>stairtruck</name>
                                            <pose>Unspecified</pose>
                                            <bndbox>
                                                <xmin>346</xmin>
                                                <ymin>130</ymin>
                                                <xmax>389</xmax>
                                                <ymax>212</ymax>
                                            </bndbox>
                                    </object>
                                    
                                    <object>
                                            <name>stairtruck</name>
                                            <pose>Unspecified</pose>
                                            <bndbox>
                                                <xmin>394</xmin>
                                                <ymin>152</ymin>
                                                <xmax>439</xmax>
                                                <ymax>256</ymax>
                                            </bndbox>
                                    </object>
                                    
                                    <object>
                                            <name>longvehicle</name>
                                            <pose>Unspecified</pose>
                                            <bndbox>
                                                <xmin>459</xmin>
                                                <ymin>412</ymin>
                                                <xmax>641</xmax>
                                                <ymax>450</ymax>
                                            </bndbox>
                                    </object>
                                    
                                    <object>
                                            <name>longvehicle</name>
                                            <pose>Unspecified</pose>
                                            <bndbox>
                                                <xmin>55</xmin>
                                                <ymin>422</ymin>
                                                <xmax>230</xmax>
                                                <ymax>461</ymax>
                                            </bndbox>
                                    </object>
                                    
                                    <object>
                                            <name>truck</name>
                                            <pose>Unspecified</pose>
                                            <bndbox>
                                                <xmin>91</xmin>
                                                <ymin>465</ymin>
                                                <xmax>199</xmax>
                                                <ymax>510</ymax>
                                            </bndbox>
                                    </object>
                                    
                                    <object>
                                            <name>longvehicle</name>
                                            <pose>Unspecified</pose>
                                            <bndbox>
                                                <xmin>436</xmin>
                                                <ymin>645</ymin>
                                                <xmax>623</xmax>
                                                <ymax>695</ymax>
                                            </bndbox>
                                    </object>
                                    
                                    <object>
                                            <name>car</name>
                                            <pose>Unspecified</pose>
                                            <bndbox>
                                                <xmin>703</xmin>
                                                <ymin>635</ymin>
                                                <xmax>734</xmax>
                                                <ymax>682</ymax>
                                            </bndbox>
                                    </object>
                                    
                                    <object>
                                            <name>car</name>
                                            <pose>Unspecified</pose>
                                            <bndbox>
                                                <xmin>794</xmin>
                                                <ymin>471</ymin>
                                                <xmax>830</xmax>
                                                <ymax>520</ymax>
                                            </bndbox>
                                    </object>
                                    
                                    <object>
                                            <name>car</name>
                                            <pose>Unspecified</pose>
                                            <bndbox>
                                                <xmin>557</xmin>
                                                <ymin>572</ymin>
                                                <xmax>604</xmax>
                                                <ymax>618</ymax>
                                            </bndbox>
                                    </object>
                                    </annotation>