<annotation verified="yes">
                                    <folder>Annotation</folder>
                                    <filename>2677</filename>
                                    <path>D:\DataSets\mine\6\mine6_output_pascal_voc\JPEGImages\2677.jpg</path>
                                    <source>
                                        <database>Unknown</database>
                                    </source>
                                    <size>
                                        <width>1024</width>
                                        <height>768</height>
                                        <depth>3</depth>
                                    </size>
                                    <segmented>0</segmented>
                                    <object>
                                            <name>car</name>
                                            <pose>Unspecified</pose>
                                            <bndbox>
                                                <xmin>455</xmin>
                                                <ymin>20</ymin>
                                                <xmax>548</xmax>
                                                <ymax>104</ymax>
                                            </bndbox>
                                    </object>
                                    
                                    <object>
                                            <name>car</name>
                                            <pose>Unspecified</pose>
                                            <bndbox>
                                                <xmin>252</xmin>
                                                <ymin>450</ymin>
                                                <xmax>346</xmax>
                                                <ymax>513</ymax>
                                            </bndbox>
                                    </object>
                                    
                                    <object>
                                            <name>car</name>
                                            <pose>Unspecified</pose>
                                            <bndbox>
                                                <xmin>282</xmin>
                                                <ymin>617</ymin>
                                                <xmax>378</xmax>
                                                <ymax>671</ymax>
                                            </bndbox>
                                    </object>
                                    
                                    <object>
                                            <name>van</name>
                                            <pose>Unspecified</pose>
                                            <bndbox>
                                                <xmin>268</xmin>
                                                <ymin>668</ymin>
                                                <xmax>399</xmax>
                                                <ymax>737</ymax>
                                            </bndbox>
                                    </object>
                                    
                                    <object>
                                            <name>car</name>
                                            <pose>Unspecified</pose>
                                            <bndbox>
                                                <xmin>538</xmin>
                                                <ymin>180</ymin>
                                                <xmax>637</xmax>
                                                <ymax>225</ymax>
                                            </bndbox>
                                    </object>
                                    
                                    <object>
                                            <name>car</name>
                                            <pose>Unspecified</pose>
                                            <bndbox>
                                                <xmin>242</xmin>
                                                <ymin>189</ymin>
                                                <xmax>343</xmax>
                                                <ymax>235</ymax>
                                            </bndbox>
                                    </object>
                                    </annotation>