<annotation verified="yes">
                                    <folder>Annotation</folder>
                                    <filename>3645</filename>
                                    <path>D:\DataSets\mine\8\mine8_output_pascal_voc\JPEGImages\3645.jpg</path>
                                    <source>
                                        <database>Unknown</database>
                                    </source>
                                    <size>
                                        <width>1024</width>
                                        <height>768</height>
                                        <depth>3</depth>
                                    </size>
                                    <segmented>0</segmented>
                                    <object>
                                            <name>bus</name>
                                            <pose>Unspecified</pose>
                                            <bndbox>
                                                <xmin>243</xmin>
                                                <ymin>142</ymin>
                                                <xmax>316</xmax>
                                                <ymax>363</ymax>
                                            </bndbox>
                                    </object>
                                    
                                    <object>
                                            <name>bus</name>
                                            <pose>Unspecified</pose>
                                            <bndbox>
                                                <xmin>277</xmin>
                                                <ymin>514</ymin>
                                                <xmax>346</xmax>
                                                <ymax>742</ymax>
                                            </bndbox>
                                    </object>
                                    
                                    <object>
                                            <name>car</name>
                                            <pose>Unspecified</pose>
                                            <bndbox>
                                                <xmin>402</xmin>
                                                <ymin>572</ymin>
                                                <xmax>447</xmax>
                                                <ymax>650</ymax>
                                            </bndbox>
                                    </object>
                                    
                                    <object>
                                            <name>car</name>
                                            <pose>Unspecified</pose>
                                            <bndbox>
                                                <xmin>416</xmin>
                                                <ymin>184</ymin>
                                                <xmax>464</xmax>
                                                <ymax>274</ymax>
                                            </bndbox>
                                    </object>
                                    
                                    <object>
                                            <name>car</name>
                                            <pose>Unspecified</pose>
                                            <bndbox>
                                                <xmin>373</xmin>
                                                <ymin>281</ymin>
                                                <xmax>416</xmax>
                                                <ymax>380</ymax>
                                            </bndbox>
                                    </object>
                                    </annotation>