<annotation verified="yes">
                                    <folder>Annotation</folder>
                                    <filename>3973</filename>
                                    <path>D:\DataSets\mine\8\mine8_output_pascal_voc\JPEGImages\3973.jpg</path>
                                    <source>
                                        <database>Unknown</database>
                                    </source>
                                    <size>
                                        <width>1024</width>
                                        <height>768</height>
                                        <depth>3</depth>
                                    </size>
                                    <segmented>0</segmented>
                                    <object>
                                            <name>car</name>
                                            <pose>Unspecified</pose>
                                            <bndbox>
                                                <xmin>661</xmin>
                                                <ymin>159</ymin>
                                                <xmax>768</xmax>
                                                <ymax>230</ymax>
                                            </bndbox>
                                    </object>
                                    
                                    <object>
                                            <name>van</name>
                                            <pose>Unspecified</pose>
                                            <bndbox>
                                                <xmin>257</xmin>
                                                <ymin>217</ymin>
                                                <xmax>376</xmax>
                                                <ymax>296</ymax>
                                            </bndbox>
                                    </object>
                                    
                                    <object>
                                            <name>car</name>
                                            <pose>Unspecified</pose>
                                            <bndbox>
                                                <xmin>175</xmin>
                                                <ymin>556</ymin>
                                                <xmax>274</xmax>
                                                <ymax>619</ymax>
                                            </bndbox>
                                    </object>
                                    </annotation>