<annotation verified="yes">
                                    <folder>Annotation</folder>
                                    <filename>4056</filename>
                                    <path>D:\DataSets\mine\9\mine9_output_pascal_voc\JPEGImages\4056.jpg</path>
                                    <source>
                                        <database>Unknown</database>
                                    </source>
                                    <size>
                                        <width>1024</width>
                                        <height>768</height>
                                        <depth>3</depth>
                                    </size>
                                    <segmented>0</segmented>
                                    <object>
                                            <name>stairtruck</name>
                                            <pose>Unspecified</pose>
                                            <bndbox>
                                                <xmin>849</xmin>
                                                <ymin>352</ymin>
                                                <xmax>910</xmax>
                                                <ymax>488</ymax>
                                            </bndbox>
                                    </object>
                                    
                                    <object>
                                            <name>stairtruck</name>
                                            <pose>Unspecified</pose>
                                            <bndbox>
                                                <xmin>474</xmin>
                                                <ymin>336</ymin>
                                                <xmax>540</xmax>
                                                <ymax>464</ymax>
                                            </bndbox>
                                    </object>
                                    
                                    <object>
                                            <name>stairtruck</name>
                                            <pose>Unspecified</pose>
                                            <bndbox>
                                                <xmin>395</xmin>
                                                <ymin>341</ymin>
                                                <xmax>458</xmax>
                                                <ymax>474</ymax>
                                            </bndbox>
                                    </object>
                                    
                                    <object>
                                            <name>stairtruck</name>
                                            <pose>Unspecified</pose>
                                            <bndbox>
                                                <xmin>319</xmin>
                                                <ymin>346</ymin>
                                                <xmax>380</xmax>
                                                <ymax>468</ymax>
                                            </bndbox>
                                    </object>
                                    
                                    <object>
                                            <name>stairtruck</name>
                                            <pose>Unspecified</pose>
                                            <bndbox>
                                                <xmin>177</xmin>
                                                <ymin>351</ymin>
                                                <xmax>242</xmax>
                                                <ymax>474</ymax>
                                            </bndbox>
                                    </object>
                                    </annotation>