<annotation verified="yes">
                                    <folder>Annotation</folder>
                                    <filename>4158</filename>
                                    <path>D:\DataSets\mine\9\mine9_output_pascal_voc\JPEGImages\4158.jpg</path>
                                    <source>
                                        <database>Unknown</database>
                                    </source>
                                    <size>
                                        <width>1024</width>
                                        <height>768</height>
                                        <depth>3</depth>
                                    </size>
                                    <segmented>0</segmented>
                                    <object>
                                            <name>truck</name>
                                            <pose>Unspecified</pose>
                                            <bndbox>
                                                <xmin>779</xmin>
                                                <ymin>84</ymin>
                                                <xmax>860</xmax>
                                                <ymax>224</ymax>
                                            </bndbox>
                                    </object>
                                    
                                    <object>
                                            <name>truck</name>
                                            <pose>Unspecified</pose>
                                            <bndbox>
                                                <xmin>708</xmin>
                                                <ymin>112</ymin>
                                                <xmax>780</xmax>
                                                <ymax>254</ymax>
                                            </bndbox>
                                    </object>
                                    
                                    <object>
                                            <name>truck</name>
                                            <pose>Unspecified</pose>
                                            <bndbox>
                                                <xmin>674</xmin>
                                                <ymin>160</ymin>
                                                <xmax>733</xmax>
                                                <ymax>254</ymax>
                                            </bndbox>
                                    </object>
                                    
                                    <object>
                                            <name>truck</name>
                                            <pose>Unspecified</pose>
                                            <bndbox>
                                                <xmin>560</xmin>
                                                <ymin>106</ymin>
                                                <xmax>671</xmax>
                                                <ymax>330</ymax>
                                            </bndbox>
                                    </object>
                                    
                                    <object>
                                            <name>car</name>
                                            <pose>Unspecified</pose>
                                            <bndbox>
                                                <xmin>224</xmin>
                                                <ymin>277</ymin>
                                                <xmax>255</xmax>
                                                <ymax>336</ymax>
                                            </bndbox>
                                    </object>
                                    
                                    <object>
                                            <name>car</name>
                                            <pose>Unspecified</pose>
                                            <bndbox>
                                                <xmin>188</xmin>
                                                <ymin>283</ymin>
                                                <xmax>223</xmax>
                                                <ymax>350</ymax>
                                            </bndbox>
                                    </object>
                                    
                                    <object>
                                            <name>car</name>
                                            <pose>Unspecified</pose>
                                            <bndbox>
                                                <xmin>148</xmin>
                                                <ymin>276</ymin>
                                                <xmax>183</xmax>
                                                <ymax>337</ymax>
                                            </bndbox>
                                    </object>
                                    
                                    <object>
                                            <name>car</name>
                                            <pose>Unspecified</pose>
                                            <bndbox>
                                                <xmin>49</xmin>
                                                <ymin>216</ymin>
                                                <xmax>86</xmax>
                                                <ymax>272</ymax>
                                            </bndbox>
                                    </object>
                                    
                                    <object>
                                            <name>car</name>
                                            <pose>Unspecified</pose>
                                            <bndbox>
                                                <xmin>16</xmin>
                                                <ymin>225</ymin>
                                                <xmax>48</xmax>
                                                <ymax>292</ymax>
                                            </bndbox>
                                    </object>
                                    
                                    <object>
                                            <name>truck</name>
                                            <pose>Unspecified</pose>
                                            <bndbox>
                                                <xmin>24</xmin>
                                                <ymin>435</ymin>
                                                <xmax>163</xmax>
                                                <ymax>489</ymax>
                                            </bndbox>
                                    </object>
                                    
                                    <object>
                                            <name>truck</name>
                                            <pose>Unspecified</pose>
                                            <bndbox>
                                                <xmin>32</xmin>
                                                <ymin>515</ymin>
                                                <xmax>163</xmax>
                                                <ymax>563</ymax>
                                            </bndbox>
                                    </object>
                                    
                                    <object>
                                            <name>van</name>
                                            <pose>Unspecified</pose>
                                            <bndbox>
                                                <xmin>827</xmin>
                                                <ymin>400</ymin>
                                                <xmax>890</xmax>
                                                <ymax>444</ymax>
                                            </bndbox>
                                    </object>
                                    
                                    <object>
                                            <name>car</name>
                                            <pose>Unspecified</pose>
                                            <bndbox>
                                                <xmin>954</xmin>
                                                <ymin>337</ymin>
                                                <xmax>1024</xmax>
                                                <ymax>384</ymax>
                                            </bndbox>
                                    </object>
                                    </annotation>